LICENSE
MANIFEST.in
README.md
VERSION
setup.cfg
setup.py
tests/__init__.py
tests/app.py
tests/conftest.py
tests/test_application.py
werkzeug_graphql/__init__.py
werkzeug_graphql/adapter.py
werkzeug_graphql/error.py
werkzeug_graphql/server.py
werkzeug_graphql.egg-info/PKG-INFO
werkzeug_graphql.egg-info/SOURCES.txt
werkzeug_graphql.egg-info/dependency_links.txt
werkzeug_graphql.egg-info/requires.txt
werkzeug_graphql.egg-info/top_level.txt
werkzeug_graphql/graphiql/index.html